gyazo_backup/__init__.py
gyazo_backup/backup.py
gyazo_backup/themes/default/index.css
gyazo_backup/themes/default/index.html
python_gyazo_backup-0.5.0.dist-info/LICENSE
python_gyazo_backup-0.5.0.dist-info/METADATA
python_gyazo_backup-0.5.0.dist-info/WHEEL
python_gyazo_backup-0.5.0.dist-info/entry_points.txt
python_gyazo_backup-0.5.0.dist-info/top_level.txt
python_gyazo_backup-0.5.0.dist-info/RECORD
