Metadata-Version: 2.1
Name: python-gyazo-backup
Version: 0.5.0
Summary: A command-tool for creating backup of Gyazo
Home-page: https://github.com/ymyzk/python-gyazo-backup
Author: Yusuke Miyazaki
Author-email: miyazaki.dev@gmail.com
License: MIT
Platform: UNKNOWN
Classifier: Development Status :: 4 - Beta
Classifier: Environment :: Console
Classifier: Operating System :: OS Independent
Classifier: License :: OSI Approved :: MIT License
Classifier: Programming Language :: Python
Classifier: Programming Language :: Python :: 3
Classifier: Programming Language :: Python :: 3.4
Classifier: Programming Language :: Python :: 3.5
Classifier: Programming Language :: Python :: 3.6
Classifier: Programming Language :: Python :: 3.7
Classifier: Programming Language :: Python :: 3.8
Classifier: Programming Language :: Python :: 3 :: Only
Classifier: Topic :: Internet
Classifier: Topic :: Utilities
Requires-Python: <4,>=3.5
Requires-Dist: Jinja2 (>=2.8)
Requires-Dist: progress (>=1.2)
Requires-Dist: python-gyazo (<3,>=2)
Provides-Extra: test
Requires-Dist: flake8 (<4.0.0,>=3.3.0) ; extra == 'test'
